{
  "$schema": "https://static.modelcontextprotocol.io/schemas/2025-07-09/server.schema.json",
  "name": "io.github.sss97133/nuke-vehicle-data",
  "description": "Access the world's largest structured collector vehicle database. 1.29M vehicles, $19.8B tracked auction GMV, 4.18M bids, 11.7M comments. Real-time vehicle search, valuations, comparables, listing extraction, and AI-powered photo analysis via YONO vision model.",
  "version": "0.3.0",
  "repository": {
    "url": "https://github.com/sss97133/nuke-mcp-server"
  },
  "packages": [
    {
      "registry_type": "npm",
      "identifier": "@sss97133/nuke-mcp-server",
      "version": "0.3.0"
    }
  ]
}
